token_yielder/__init__.py
token_yielder/__version__.py
token_yielder/connect.py
token_yielder/errors.py
token_yielder-1.0.1.dist-info/licenses/LICENSE.md
token_yielder-1.0.1.dist-info/METADATA
token_yielder-1.0.1.dist-info/WHEEL
token_yielder-1.0.1.dist-info/top_level.txt
token_yielder-1.0.1.dist-info/RECORD
