Metadata-Version: 2.4
Name: token_yielder
Version: 1.0.1
Summary: PYTHON module to generate and rotate token
Author: Rakesh
Author-email: Rakesh <rakeshpraneel@gmail.com>
License: MIT
Project-URL: Source, https://github.com/rakeshpraneel/token-yielder
Classifier: License :: OSI Approved :: MIT License
Classifier: Programming Language :: Python :: 3
Classifier: Operating System :: OS Independent
Requires-Python: >=3.6
License-File: LICENSE.md
Dynamic: author
Dynamic: license-file
Dynamic: requires-python
